{
  "version": "1.1.0",
  "diagrams": [
    {
      "ordinal": 0,
      "scrollPosition": {
        "x": 0,
        "y": 0
      },
      "nodes": [
        {
          "location": {
            "x": 0,
            "y": 0
          },
          "nodeIndex": "dBox",
          "nodeLineageTag": "a9e58253-6282-47fb-aaf7-be6828713629",
          "size": {
            "height": 104,
            "width": 234
          },
          "zIndex": 13,
          "expandedHeight": 200
        },
        {
          "location": {
            "x": 0,
            "y": 126.8399832515006
          },
          "nodeIndex": "dCalendario",
          "nodeLineageTag": "5be52927-945a-4435-8b63-242e81b028f3",
          "size": {
            "height": 200,
            "width": 234
          },
          "zIndex": 7
        },
        {
          "location": {
            "x": 0,
            "y": 267.71064452142855
          },
          "nodeIndex": "dHeadcount",
          "nodeLineageTag": "d24c28e9-5fe9-4b7b-a7d6-30cfc53262ea",
          "size": {
            "height": 72,
            "width": 234
          },
          "zIndex": 5,
          "expandedHeight": 176
        },
        {
          "location": {
            "x": 0,
            "y": 398.737290717707
          },
          "nodeIndex": "dHora",
          "nodeLineageTag": "31c16edf-bc81-4017-8700-bb1402c82408",
          "size": {
            "height": 72,
            "width": 234
          },
          "zIndex": 6,
          "expandedHeight": 224
        },
        {
          "location": {
            "x": 0,
            "y": 579.21460655816315
          },
          "nodeIndex": "dZona",
          "nodeLineageTag": "c52e1011-b1c3-4d7e-b16f-5b47422470ba",
          "size": {
            "height": 104,
            "width": 234
          },
          "zIndex": 12,
          "expandedHeight": 128
        },
        {
          "location": {
            "x": 0,
            "y": 738.25756482648546
          },
          "nodeIndex": "niveis",
          "nodeLineageTag": "e292a6e7-a085-4193-8e37-e7e509f643ad",
          "size": {
            "height": 72,
            "width": 234
          },
          "zIndex": 8,
          "expandedHeight": 104
        },
        {
          "location": {
            "x": 620.14532644783912,
            "y": 0
          },
          "nodeIndex": "fstatus_olpn_periodic",
          "nodeLineageTag": "d15d9ef1-dbc8-461b-a7f3-6e65e1417022",
          "size": {
            "height": 104,
            "width": 234
          },
          "zIndex": 4,
          "expandedHeight": 300
        },
        {
          "location": {
            "x": 1070.4466378220288,
            "y": 31.800824842774546
          },
          "nodeIndex": "Medidas",
          "nodeLineageTag": "197c8b73-a04c-43de-9174-105764e0dbc0",
          "size": {
            "height": 72,
            "width": 234
          },
          "zIndex": 2,
          "expandedHeight": 104
        },
        {
          "location": {
            "x": 1103.5853376135055,
            "y": 157.91547327218632
          },
          "nodeIndex": "dHora_agora",
          "nodeLineageTag": "f2fb1131-6dc3-4823-96f1-35772ad16e85",
          "size": {
            "height": 72,
            "width": 234
          },
          "zIndex": 3,
          "expandedHeight": 128
        },
        {
          "location": {
            "x": 620.90810551554648,
            "y": 171.97812672614785
          },
          "nodeIndex": "fpedidos_cancelado_periodic",
          "nodeLineageTag": "c02ec9fc-673c-4729-9761-c25a9af94203",
          "size": {
            "height": 72,
            "width": 234
          },
          "zIndex": 9,
          "expandedHeight": 300
        },
        {
          "location": {
            "x": 625.86014236224491,
            "y": 383.37809881198211
          },
          "nodeIndex": "fprodutividade_picking_periodic",
          "nodeLineageTag": "eef5f1d2-7e8f-4be7-a3ff-75c184af72db",
          "size": {
            "height": 300,
            "width": 234
          },
          "zIndex": 14
        },
        {
          "location": {
            "x": 613.861439779352,
            "y": 566.5914079530387
          },
          "nodeIndex": "fprodutividade_putaway_periodic",
          "nodeLineageTag": "0054c7a3-37bb-4e8c-ab40-de1d5a71e16b",
          "size": {
            "height": 128,
            "width": 234
          },
          "zIndex": 10,
          "expandedHeight": 300
        },
        {
          "location": {
            "x": 890.81477404315774,
            "y": 694.83006587326668
          },
          "nodeIndex": "fProdutividade",
          "nodeLineageTag": "239a7357-f497-4fb8-abe1-71fa9c0364f2",
          "size": {
            "height": 176,
            "width": 234
          },
          "zIndex": 11
        },
        {
          "location": {
            "x": 1201.5533621779714,
            "y": 687.2303161175156
          },
          "nodeIndex": "fConferencia",
          "nodeLineageTag": "8196f306-ee99-4504-9317-58696c5433fc",
          "size": {
            "height": 152,
            "width": 234
          },
          "zIndex": 1
        }
      ],
      "name": "Todas as tabelas",
      "zoomValue": 70.95554390096882,
      "pinKeyFieldsToTop": false,
      "showExtraHeaderInfo": false,
      "hideKeyFieldsWhenCollapsed": false,
      "tablesLocked": false
    }
  ],
  "selectedDiagram": "Todas as tabelas",
  "defaultDiagram": "Todas as tabelas"
}